nagiosplugin-stubs/__init__.pyi
nagiosplugin-stubs/check.pyi
nagiosplugin-stubs/compat.pyi
nagiosplugin-stubs/context.pyi
nagiosplugin-stubs/cookie.pyi
nagiosplugin-stubs/error.pyi
nagiosplugin-stubs/logtail.pyi
nagiosplugin-stubs/metric.pyi
nagiosplugin-stubs/multiarg.pyi
nagiosplugin-stubs/output.pyi
nagiosplugin-stubs/performance.pyi
nagiosplugin-stubs/range.pyi
nagiosplugin-stubs/resource.pyi
nagiosplugin-stubs/result.pyi
nagiosplugin-stubs/runtime.pyi
nagiosplugin-stubs/state.pyi
nagiosplugin-stubs/summary.pyi
nagiosplugin-stubs/version.pyi
nagiosplugin_stubs-0.6.4.dist-info/LICENSE
nagiosplugin_stubs-0.6.4.dist-info/METADATA
nagiosplugin_stubs-0.6.4.dist-info/WHEEL
nagiosplugin_stubs-0.6.4.dist-info/RECORD
