Metadata-Version: 2.1
Name: nagiosplugin-stubs
Version: 0.6.4
Summary: Type stubs for the nagiosplugin package.
Home-page: https://github.com/Josef-Friedrich/nagiosplugin-stubs
License: MIT
Author: Josef Friedrich
Author-email: josef@friedrich.rocks
Requires-Python: >=3.8,<4.0
Classifier: Development Status :: 5 - Production/Stable
Classifier: License :: OSI Approved :: MIT License
Classifier: Programming Language :: Python :: 3
Classifier: Programming Language :: Python :: 3.8
Classifier: Programming Language :: Python :: 3.9
Classifier: Programming Language :: Python :: 3.10
Classifier: Programming Language :: Python :: 3.11
Classifier: Programming Language :: Python :: 3.12
Classifier: Programming Language :: Python :: 3 :: Only
Classifier: Typing :: Stubs Only
Requires-Dist: typing-extensions (>=4.3.0,<5.0.0)
Project-URL: Repository, https://github.com/Josef-Friedrich/nagiosplugin-stubs
